src/station_data/__init__.py
src/station_data/main.py
src/station_data/preprocessing.py
stationdata-0.1.0.dist-info/METADATA
stationdata-0.1.0.dist-info/WHEEL
stationdata-0.1.0.dist-info/licenses/LICENSE
stationdata-0.1.0.dist-info/RECORD
